MANIFEST.in
README.rst
setup.py
openvas_to_report/__init__.py
openvas_to_report/api.py
openvas_to_report/openvas_cutter.py
openvas_to_report/openvas_to_document.py
openvas_to_report.egg-info/PKG-INFO
openvas_to_report.egg-info/SOURCES.txt
openvas_to_report.egg-info/dependency_links.txt
openvas_to_report.egg-info/entry_points.txt
openvas_to_report.egg-info/requires.txt
openvas_to_report.egg-info/top_level.txt
openvas_to_report/examples/__init__.py
openvas_to_report/libs/__init__.py
openvas_to_report/libs/data/__init__.py
openvas_to_report/libs/data/config.py
openvas_to_report/libs/data/parsed_data.py
openvas_to_report/libs/exporters/__init__.py
openvas_to_report/libs/exporters/excel.py
openvas_to_report/libs/exporters/word.py
openvas_to_report/libs/parsers/__init__.py
openvas_to_report/libs/parsers/openvas_parser.py
openvas_to_report/libs/translations/__init__.py
openvas_to_report/libs/translations/excel/en.json
openvas_to_report/libs/translations/excel/es.json
openvas_to_report/test/__init__.py