Metadata-Version: 1.1
Name: openvas-to-report
Version: 1.0.0
Summary: OpenVAS2Report: A set of tools to manager OpenVAS XML report files.
Home-page: https://github.com/cr0hn/openvas_to_report
Author: cr0hn
Author-email: cr0hn<-at->cr0hn.com
License: BSD
Platform: UNKNOWN
Classifier: Environment :: Console
Classifier: Intended Audience :: System Administrators
Classifier: Intended Audience :: Other Audience
Classifier: License :: OSI Approved :: BSD License
Classifier: Operating System :: MacOS
Classifier: Operating System :: Microsoft :: Windows
Classifier: Operating System :: POSIX
Classifier: Programming Language :: Python :: 3
Classifier: Topic :: Security
